showdown_anal_bot/__init__.py
showdown_anal_bot/__main__.py
showdown_anal_bot/bot.py
showdown_anal_bot/cfg.py
showdown_anal_bot/cli.py
showdown_anal_bot/command.py
showdown_anal_bot/commands.py
showdown_anal_bot/constants.py
showdown_anal_bot/helpers.py
showdown_anal_bot/messages.py
showdown_anal_bot/parser.py
showdown_anal_bot/stalk.py
showdown_anal_bot/team_extractor.py
showdown_anal_bot/gui/__init__.py
showdown_anal_bot/gui/download_sprites.py
showdown_anal_bot/gui/gui.py
showdown_anal_bot/gui/sprites.py
showdown_anal_bot-0.0.2.dist-info/LICENSE
showdown_anal_bot-0.0.2.dist-info/METADATA
showdown_anal_bot-0.0.2.dist-info/WHEEL
showdown_anal_bot-0.0.2.dist-info/top_level.txt
showdown_anal_bot-0.0.2.dist-info/RECORD
