Metadata-Version: 2.1
Name: showdown-anal-bot
Version: 0.0.2
Summary: Pokemon Showdown analysis tools
Home-page: https://github.com/yoursred/showdown-anal-bot
Author: yoursred
Author-email: yoursred@yoursred.com
License: UNKNOWN
Project-URL: Bug Tracker, https://github.com/yoursred/showdown-anal-bot/issues
Platform: UNKNOWN
Classifier: Programming Language :: Python :: 3
Classifier: License :: OSI Approved :: The Unlicense (Unlicense)
Classifier: Operating System :: OS Independent
Requires-Python: >=3.10
License-File: LICENSE
Requires-Dist: showdownpy
Requires-Dist: requests
